__init__.py
pandas_term/__init__.py
pandas_term/main.py
pandas_term/py.typed
pandas_term/cli/__init__.py
pandas_term/cli/aggregate_commands.py
pandas_term/cli/filter_commands.py
pandas_term/cli/options.py
pandas_term/cli/stats_commands.py
pandas_term/cli/transform_commands.py
pandas_term/cli/validators.py
pandas_term/core/__init__.py
pandas_term/core/io_operations.py
pandas_term/core/transforms.py
pandas_term-0.1.2.dist-info/licenses/LICENSE
pandas_term-0.1.2.dist-info/METADATA
pandas_term-0.1.2.dist-info/WHEEL
pandas_term-0.1.2.dist-info/entry_points.txt
pandas_term-0.1.2.dist-info/top_level.txt
pandas_term-0.1.2.dist-info/RECORD
