Metadata-Version: 2.4
Name: pandas-term
Version: 0.1.2
Summary: CLI bringing pandas operations to the command line
Author: Katie Gardner
License: MIT License
Project-URL: Homepage, https://github.com/KatieLG/pandas-term
Project-URL: Repository, https://github.com/KatieLG/pandas-term
Keywords: pandas,cli,terminal,dataframe,csv,data,etl
Classifier: Development Status :: 4 - Beta
Classifier: Environment :: Console
Classifier: Intended Audience :: Developers
Classifier: License :: OSI Approved :: MIT License
Classifier: Operating System :: OS Independent
Classifier: Programming Language :: Python :: 3
Classifier: Programming Language :: Python :: 3.10
Classifier: Programming Language :: Python :: 3.11
Classifier: Programming Language :: Python :: 3.12
Classifier: Programming Language :: Python :: 3.13
Classifier: Topic :: Utilities
Classifier: Typing :: Typed
Requires-Python: >=3.10
License-File: LICENSE
Requires-Dist: openpyxl>=3.1.5
Requires-Dist: pandas>=2.3.3
Requires-Dist: pyarrow>=19.0.0
Requires-Dist: tabulate>=0.9.0
Requires-Dist: typer>=0.20.0
Dynamic: license-file
